pii_engine/__init__.py
pii_engine/orm.py
pii_engine/config/__init__.py
pii_engine/config/config.py
pii_engine/config/fabricator.json
pii_engine/config/settings.py
pii_engine/core/__init__.py
pii_engine/core/clean_processor.py
pii_engine/core/pseudonymizer.py
pii_engine/core/token_generator.py
pii_engine/utils/__init__.py
pii_engine/utils/integration_helpers.py
pii_engine/wrappers/__init__.py
pii_engine/wrappers/field_reverse_wrapper.py
pii_engine/wrappers/integration_wrappers.py
pii_engine/wrappers/phase2_wrapper.py
tns_pii_engine-1.0.2.dist-info/licenses/LICENSE
tns_pii_engine-1.0.2.dist-info/METADATA
tns_pii_engine-1.0.2.dist-info/WHEEL
tns_pii_engine-1.0.2.dist-info/top_level.txt
tns_pii_engine-1.0.2.dist-info/RECORD
